consts/__init_.py
consts/__init__.py
consts/constants.py
entities/__init__.py
entities/partial_log_entry.py
entities/performance_log_entry.py
helpers/__init__.py
helpers/bcolors.py
helpers/calculator.py
helpers/dic_builder.py
helpers/file_writer.py
helpers/group.py
helpers/id_generator.py
helpers/logger.py
helpers/table_printer.py
pytest_performancetotal/__init__.py
pytest_performancetotal/performance.py
pytest_performancetotal/performance_analyzer.py
pytest_performancetotal/performance_cache.py
pytest_performancetotal/performancetotal.py
pytest_performancetotal-0.2.11.dist-info/licenses/LICENSE
pytest_performancetotal-0.2.11.dist-info/METADATA
pytest_performancetotal-0.2.11.dist-info/WHEEL
pytest_performancetotal-0.2.11.dist-info/entry_points.txt
pytest_performancetotal-0.2.11.dist-info/top_level.txt
pytest_performancetotal-0.2.11.dist-info/RECORD
