Metadata-Version: 2.4
Name: pytest-performancetotal
Version: 0.2.11
Summary: A performance plugin for pytest
Home-page: https://github.com/tzurp/pytest_performancetotal
Author: Tzur Paldi
Author-email: tzur.paldi@outlook.com
Maintainer: Tzur Paldi
Maintainer-email: tzur.paldi@outlook.com
License: Apache-2.0
Project-URL: Bug Tracker, https://github.com/tzurp/pytest_performancetotal/issues
Project-URL: Documentation, https://github.com/tzurp/pytest_performancetotal#readme
Project-URL: Source Code, https://github.com/tzurp/pytest_performancetotal
Keywords: pytest plugin performance playwright
Classifier: Development Status :: 5 - Production/Stable
Classifier: Framework :: Pytest
Classifier: License :: OSI Approved :: Apache Software License
License-File: LICENSE
Requires-Dist: filelock>=3.13.0
Dynamic: author
Dynamic: author-email
Dynamic: classifier
Dynamic: description
Dynamic: description-content-type
Dynamic: home-page
Dynamic: keywords
Dynamic: license
Dynamic: license-file
Dynamic: maintainer
Dynamic: maintainer-email
Dynamic: project-url
Dynamic: requires-dist
Dynamic: summary
